typer_aliases/__init__.py
typer_aliases/_version.py
typer_aliases/core.py
typer_aliases/format.py
typer_aliases/py.typed
typer_aliases-0.2.1.dist-info/METADATA
typer_aliases-0.2.1.dist-info/WHEEL
typer_aliases-0.2.1.dist-info/licenses/LICENSE
typer_aliases-0.2.1.dist-info/RECORD
