Metadata-Version: 2.4
Name: typer-aliases
Version: 0.2.1
Summary: Command aliases for Typer CLI applications
Project-URL: Homepage, https://github.com/rdawebb/typer-aliases
Project-URL: Documentation, https://github.com/rdawebb/typer-aliases#readme
Project-URL: Repository, https://github.com/rdawebb/typer-aliases
Project-URL: Changelog, https://github.com/rdawebb/typer-aliases/blob/main/CHANGELOG.md
Project-URL: Issues, https://github.com/rdawebb/typer-aliases/issues
Author: Rob Webb
License: MIT
License-File: LICENSE
Keywords: aliases,cli,click,command-line,typer
Classifier: Development Status :: 4 - Beta
Classifier: Intended Audience :: Developers
Classifier: License :: OSI Approved :: MIT License
Classifier: Programming Language :: Python :: 3
Classifier: Programming Language :: Python :: 3.9
Classifier: Programming Language :: Python :: 3.10
Classifier: Programming Language :: Python :: 3.11
Classifier: Programming Language :: Python :: 3.12
Classifier: Programming Language :: Python :: 3.13
Classifier: Programming Language :: Python :: 3.14
Classifier: Topic :: Software Development :: Libraries :: Python Modules
Classifier: Topic :: System :: Shells
Classifier: Typing :: Typed
Requires-Python: >=3.9
Requires-Dist: click<9.0.0,>=8.0.0
Requires-Dist: typer>=0.9.0
Provides-Extra: dev
Requires-Dist: prek<1.0.0,>=0.2.27; extra == 'dev'
Requires-Dist: pytest-cov<8.0.0,>=7.0.0; extra == 'dev'
Requires-Dist: pytest<10.0.0,>=8.0.0; extra == 'dev'
Requires-Dist: ruff<15.0.0,>=0.14.0; extra == 'dev'
Requires-Dist: rust-just<2.0.0,>=1.46.0; extra == 'dev'
Requires-Dist: ty<0.1.0,>=0.0.10; extra == 'dev'
